web3_wrapped_contract/__init__.py
web3_wrapped_contract/contract_utils.py
web3_wrapped_contract/no_account_exception.py
web3_wrapped_contract/wrapped_contract.py
web3_wrapped_contract-0.0.16.dist-info/LICENSE
web3_wrapped_contract-0.0.16.dist-info/METADATA
web3_wrapped_contract-0.0.16.dist-info/WHEEL
web3_wrapped_contract-0.0.16.dist-info/top_level.txt
web3_wrapped_contract-0.0.16.dist-info/RECORD
