Metadata-Version: 2.1
Name: web3-wrapped-contract
Version: 0.0.16
Summary: web3_wrapped_contract
Home-page: https://github.com/kkristof200/py_web3_wrapped_contract
Author: Kristóf-Attila Kovács
License: UNKNOWN
Platform: UNKNOWN
Classifier: Programming Language :: Python :: 3.4
Classifier: Programming Language :: Python :: 3.5
Classifier: Programming Language :: Python :: 3.6
Classifier: Programming Language :: Python :: 3.7
Classifier: Programming Language :: Python :: 3.8
Classifier: Programming Language :: Python :: 3.9
Classifier: License :: OSI Approved :: MIT License
Classifier: Operating System :: OS Independent
Requires-Python: >=3.4
License-File: LICENSE
Requires-Dist: eth-account (>=0.5.6)
Requires-Dist: setuptools (>=59.6.0)
Requires-Dist: web3 (>=5.25.0)
